concretedropout/__init__.py
concretedropout/pytorch.py
concretedropout/tensorflow.py
concretedropout-0.2.1.dist-info/METADATA
concretedropout-0.2.1.dist-info/WHEEL
concretedropout-0.2.1.dist-info/licenses/LICENSE
concretedropout-0.2.1.dist-info/RECORD
