Metadata-Version: 2.1
Name: ConcreteDropout
Version: 0.2.1
Summary: Concrete Dropout implementation for Tensorflow 2 and PyTorch
Project-URL: Homepage, https://github.com/aurelio-amerio/ConcreteDropout-TF2
Project-URL: Bug Tracker, https://github.com/aurelio-amerio/ConcreteDropout-TF2/issues
Author-email: Aurelio Amerio <aurelio.amerio@ific.uv.es>
License: MIT License
Classifier: License :: OSI Approved :: MIT License
Classifier: Operating System :: OS Independent
Classifier: Programming Language :: Python :: 3
Requires-Python: >=3.7
